LICENSE
README.md
setup.cfg
setup.py
kachery_cloud/TemporaryDirectory.py
kachery_cloud/__init__.py
kachery_cloud/_client_keys.py
kachery_cloud/_custom_storage_backend.py
kachery_cloud/_fs_operations.py
kachery_cloud/_get_kachery_gateway_url.py
kachery_cloud/_get_local_client_config.py
kachery_cloud/_json_stringify_deterministic.py
kachery_cloud/_kachery_gateway_request.py
kachery_cloud/_load_github_file.py
kachery_cloud/_safe_pickle.py
kachery_cloud/_serialize.py
kachery_cloud/_sha1_of_dict.py
kachery_cloud/_sha1_of_string.py
kachery_cloud/admin_delete_file.py
kachery_cloud/cat_file.py
kachery_cloud/cli.py
kachery_cloud/core.py
kachery_cloud/get_client_id.py
kachery_cloud/get_kachery_cloud_dir.py
kachery_cloud/init.py
kachery_cloud/link_file.py
kachery_cloud/load_bytes.py
kachery_cloud/load_file.py
kachery_cloud/mutable_local.py
kachery_cloud/request_file.py
kachery_cloud/store_file.py
kachery_cloud/store_file_local.py
kachery_cloud.egg-info/PKG-INFO
kachery_cloud.egg-info/SOURCES.txt
kachery_cloud.egg-info/dependency_links.txt
kachery_cloud.egg-info/entry_points.txt
kachery_cloud.egg-info/requires.txt
kachery_cloud.egg-info/top_level.txt
kachery_cloud/zenodo_upload/__init__.py
kachery_cloud/zenodo_upload/zenodo_upload.py