Metadata-Version: 2.1
Name: kachery-cloud
Version: 0.4.7
Summary: None
Home-page: https://github.com/flatironinstitute/kachery-cloud
Author: Jeremy Magland
Author-email: jmagland@flatironinstitute.org
Project-URL: Bug Tracker, https://github.com/flatironinstitute/kachery-cloud/issues
Classifier: Programming Language :: Python :: 3
Classifier: License :: OSI Approved :: Apache Software License
Classifier: Operating System :: OS Independent
License-File: LICENSE
Requires-Dist: requests
Requires-Dist: click
Requires-Dist: simplejson
Requires-Dist: cryptography
Requires-Dist: pubnub>=7.2.0
Requires-Dist: dask[distributed]
